truthscore/__init__.py
truthscore/factual_correctness.py
truthscore-0.3.0.dist-info/METADATA
truthscore-0.3.0.dist-info/WHEEL
truthscore-0.3.0.dist-info/RECORD
