Metadata-Version: 2.1
Name: truthscore
Version: 0.3.0
Summary: A fast, modular reimplementation of RAGAS's FactualCorrectness metric, supporting both open-weight and dedicated LLMs.
License: MIT
Keywords: nlp,factuality,evaluation,llm,RAGAS,hallucination,truthfulness,benchmark
Author: Giovanni Gatti Pinheiro
Author-email: giovanni.gatti.pinheiro@gmail.com
Requires-Python: >=3.10,<3.14
Classifier: Development Status :: 4 - Beta
Classifier: Intended Audience :: Developers
Classifier: Intended Audience :: Science/Research
Classifier: License :: OSI Approved :: MIT License
Classifier: Operating System :: OS Independent
Classifier: Programming Language :: Python :: 3
Classifier: Programming Language :: Python :: 3.10
Classifier: Programming Language :: Python :: 3.11
Classifier: Programming Language :: Python :: 3.12
Classifier: Programming Language :: Python :: 3.13
Classifier: Topic :: Scientific/Engineering
Classifier: Topic :: Scientific/Engineering :: Artificial Intelligence
Classifier: Topic :: Scientific/Engineering :: Information Analysis
Classifier: Topic :: Software Development :: Libraries :: Python Modules
Classifier: Topic :: Text Processing :: Linguistic
Provides-Extra: open
Requires-Dist: langchain-ollama (>=0.3.3,<1.0.0) ; extra == "open"
Requires-Dist: ragas (>=0.2.15,<1.0.0)
Requires-Dist: sentence-transformers (>=4.1.0,<5.0.0)
Requires-Dist: sentencepiece (>=0.2.0,<1.0.0) ; extra == "open"
